import_from_gist/__init__.py
import_from_gist/import_from_gist.py
import_from_gist-0.1.0.dist-info/LICENSE
import_from_gist-0.1.0.dist-info/METADATA
import_from_gist-0.1.0.dist-info/WHEEL
import_from_gist-0.1.0.dist-info/top_level.txt
import_from_gist-0.1.0.dist-info/RECORD
